VideoOpinionMining/__init__.py
VideoOpinionMining/vem.py
VideoOpinionMining-1.2.dist-info/LICENSE
VideoOpinionMining-1.2.dist-info/METADATA
VideoOpinionMining-1.2.dist-info/WHEEL
VideoOpinionMining-1.2.dist-info/top_level.txt
VideoOpinionMining-1.2.dist-info/RECORD
