Metadata-Version: 2.1
Name: VideoOpinionMining
Version: 1.2
Summary: This package receives an mp4 file classfying it according to its emotions and generating a heat map
Author-email: Artur Lima <vligmart@gmail.com>
Project-URL: Homepage, https://github.com/Labic-ICMC-USP/VEM
Project-URL: Example, https://colab.research.google.com/drive/1sYAYRxFdpa86Huxm-KVkEvQo6x8ZmgS6?authuser=1
Classifier: Programming Language :: Python :: 3
Classifier: License :: OSI Approved :: MIT License
Classifier: Operating System :: OS Independent
Requires-Python: >=3.7
License-File: LICENSE
